doT/__init__.py
doT/tests/__init__.py
doT/tests/__snapshots__/test_dot/test_template[arrays.tmpl].json
doT/tests/__snapshots__/test_dot/test_template[conditionals.tmpl].json
doT/tests/__snapshots__/test_dot/test_template[encode.tmpl].json
doT/tests/__snapshots__/test_dot/test_template[evaluation.tmpl].json
doT/tests/__snapshots__/test_dot/test_template[interpolation.tmpl].json
doT/tests/__snapshots__/test_dot/test_template[issue_4.tmpl].json
doT/tests/__snapshots__/test_dot/test_template[partials.tmpl].json
doT/tests/conftest.py
doT/tests/test_dot/arrays.tmpl
doT/tests/test_dot/conditionals.tmpl
doT/tests/test_dot/encode.tmpl
doT/tests/test_dot/evaluation.tmpl
doT/tests/test_dot/interpolation.tmpl
doT/tests/test_dot/issue_4.tmpl
doT/tests/test_dot/partials.tmpl
doT/tests/test_dot.py
dot_js_py-2.0.0.dist-info/LICENSE
dot_js_py-2.0.0.dist-info/METADATA
dot_js_py-2.0.0.dist-info/WHEEL
dot_js_py-2.0.0.dist-info/RECORD
