Metadata-Version: 2.1
Name: dot-js-py
Version: 2.0.0
Summary: A python implementation of the famous js template engine. doT.js.
License: MIT
Author: lucemia
Author-email: lucemia@gmail.com
Requires-Python: >=3.8.1,<4.0.0
Classifier: License :: OSI Approved :: MIT License
Classifier: Programming Language :: Python :: 3
Classifier: Programming Language :: Python :: 3.9
Classifier: Programming Language :: Python :: 3.10
Classifier: Programming Language :: Python :: 3.11
